jdla_basic/__init__.py
jdla_basic/basic_opeartions.py
jdla_basic-1.0.dist-info/LICENSE
jdla_basic-1.0.dist-info/METADATA
jdla_basic-1.0.dist-info/WHEEL
jdla_basic-1.0.dist-info/top_level.txt
jdla_basic-1.0.dist-info/RECORD
